Workbook

Sheet Dashboard
A1: Sales Performance Dashboard
A3: Total Net Sales | D3: Total Orders | G3: Total Units Sold
A4: =KPI_Analysis!B2 -> 655400 | D4: =KPI_Analysis!B4 -> 30 | G4: =KPI_Analysis!B5 -> 75

Sheet Business_Insights
A1: SALES PERFORMANCE ANALYSIS — KEY FINDINGS
A3: Finding | B3: Observation
A4: Top-performing city | B4: Bengaluru generated ₹182,700 in net sales.
A5: Top-performing product | B5: Laptops generated ₹483,500 in net sales.
A6: Revenue concentration | B6: Laptops contributed approximately 73.8% of total net sales.
A7: Lowest-performing city | B7: Navi Mumbai generated ₹72,650 in net sales.

Sheet Product_Analysis
A3: Row Labels | B3: Sum of Net_Sales_INR
A4: Laptop | B4: 483500
A5: Monitor | B5: 98600
A6: Headphones | B6: 32200
A7: Keyboard | B7: 28250
A8: Mouse | B8: 12850
A9: Grand Total | B9: 655400

Sheet City_Analysis
A3: Row Labels | B3: Sum of Net_Sales_INR
A4: Bengaluru | B4: 182700
A5: Delhi | B5: 142300
A6: Pune | B6: 132200
A7: Mumbai | B7: 125550
A8: Navi Mumbai | B8: 72650
A9: Grand Total | B9: 655400

Sheet KPI_Analysis
A1: Metric | B1: Result
A2: Total Net Sales | B2: =SUM(Sales_Data!L2:L31) -> 655400
A3: Average Sales per order | B3: =AVERAGE(Sales_Data!L2:L31) -> 21846.667
A4: Total Orders | B4: =COUNTA(Sales_Data!A2:A31) -> 30
A5: Total Units Sold | B5: =SUM(Sales_Data!G2:G31) -> 75
A6: Online Net Sales | B6: =SUMIF(Sales_Data!J2:J31,"Online",Sales_Data!L2:L31) -> 476650
A7: Electronics Net Sales | B7: =SUMIF(Sales_Data!F2:F31,"Electronics",Sales_Data!L2:L31) -> 582100
A8: Mumbai Order Counts | B8: =COUNTIF(Sales_Data!C2:C31,"Mumbai") -> 7

Sheet Sales_Data
A1: Order_ID | B1: Order_Date | C1: City | D1: Region | E1: Product | F1: Category | G1: Units_Sold | H1: Unit_Price_INR | I1: Discount_INR | J1: Sales_Channel | K1: Payment_Mode | L1: Net_Sales_INR
A2: 3001 | B2: 46025 | C2: Mumbai | D2: West | E2: Laptop | F2: Electronics | G2: 1 | H2: 48000 | I2: 2000 | J2: Online | K2: UPI | L2: =G2*H2-I2 -> 46000
A3: 3002 | B3: 46026 | C3: Pune | D3: West | E3: Mouse | F3: Accessories | G3: 3 | H3: 600 | I3: 0 | J3: Store | K3: Cash | L3: =G3*H3-I3 -> 1800
A4: 3003 | B4: 46027 | C4: Delhi | D4: North | E4: Monitor | F4: Electronics | G4: 2 | H4: 11000 | I4: 1000 | J4: Online | K4: Credit Card | L4: =G4*H4-I4 -> 21000
A5: 3004 | B5: 46028 | C5: Navi Mumbai | D5: West | E5: Keyboard | F5: Accessories | G5: 2 | H5: 1600 | I5: 200 | J5: Store | K5: UPI | L5: =G5*H5-I5 -> 3000
A6: 3005 | B6: 46030 | C6: Bengaluru | D6: South | E6: Headphones | F6: Accessories | G6: 4 | H6: 2000 | I6: 500 | J6: Online | K6: Credit Card | L6: =G6*H6-I6 -> 7500
A7: 3006 | B7: 46031 | C7: Mumbai | D7: West | E7: Monitor | F7: Electronics | G7: 1 | H7: 12000 | I7: 500 | J7: Store | K7: UPI | L7: =G7*H7-I7 -> 11500
A8: 3007 | B8: 46032 | C8: Delhi | D8: North | E8: Laptop | F8: Electronics | G8: 2 | H8: 50000 | I8: 3000 | J8: Online | K8: Net Banking | L8: =G8*H8-I8 -> 97000
A9: 3008 | B9: 46033 | C9: Pune | D9: West | E9: Keyboard | F9: Accessories | G9: 3 | H9: 1500 | I9: 0 | J9: Online | K9: UPI | L9: =G9*H9-I9 -> 4500
A10: 3009 | B10: 46034 | C10: Bengaluru | D10: South | E10: Laptop | F10: Electronics | G10: 1 | H10: 52000 | I10: 2500 | J10: Store | K10: Credit Card | L10: =G10*H10-I10 -> 49500
A11: 3010 | B11: 46036 | C11: Navi Mumbai | D11: West | E11: Mouse | F11: Accessories | G11: 5 | H11: 550 | I11: 100 | J11: Online | K11: UPI | L11: =G11*H11-I11 -> 2650
A12: 3011 | B12: 46037 | C12: Mumbai | D12: West | E12: Headphones | F12: Accessories | G12: 2 | H12: 2500 | I12: 300 | J12: Online | K12: Credit Card | L12: =G12*H12-I12 -> 4700
A13: 3012 | B13: 46038 | C13: Delhi | D13: North | E13: Monitor | F13: Electronics | G13: 1 | H13: 11500 | I13: 0 | J13: Store | K13: Cash | L13: =G13*H13-I13 -> 11500
... A31: 3030 | B31: 46073 | C31: Navi Mumbai | D31: West | E31: Keyboard | F31: Accessories | G31: 4 | H31: 1550 | I31: 200 | J31: Store | K31: Cash | L31: =G31*H31-I31 -> 6000
